Metadata-Version: 2.1
Name: odoo14-addon-sequence_reset_period
Version: 14.0.1.0.1.dev10
Summary: Auto-generate yearly/monthly/weekly/daily sequence period ranges
Home-page: https://github.com/OCA/server-ux
Author: Creu Blanca, Odoo Community Association (OCA)
Author-email: support@odoo-community.org
License: LGPL-3
Classifier: Programming Language :: Python
Classifier: Framework :: Odoo
Classifier: Framework :: Odoo :: 14.0
Classifier: License :: OSI Approved :: GNU Lesser General Public License v3 (LGPLv3)
Requires-Python: >=3.6
Requires-Dist: odoo<14.1dev,>=14.0a
